<?xml version="1.0" encoding="UTF-8" standalone="no"?>
<datamodel-type xmlns="http://www.efaps.org/xsd" xmlns:xsi="http://www.w3.org/2001/XMLSchema-instance" xsi:schemaLocation="http://www.efaps.org/xsd http://www.efaps.org/xsd/eFaps_1.0.xsd">

    <uuid>5248c84b-2724-4c46-afd3-b937959a74d7</uuid>
    <file-application>eFaps-Kernel</file-application>
        <definition>
        <version-expression>(version==latest)</version-expression>
        <name>GeneralStoreAbstract</name>
        <parent>GeneralInstance</parent>
        <purpose abstract="true"/>
        

        <attribute>
            <name>FileLength</name>
            <type>Long</type>
            <sqltable>GeneralStoreSQLTable</sqltable>
            <sqlcolumn>FILELENGTH</sqlcolumn>
        </attribute>
        <attribute>
            <name>FileName</name>
            <type>String</type>
            <sqltable>GeneralStoreSQLTable</sqltable>
            <sqlcolumn>FILENAME</sqlcolumn>
        </attribute>
    </definition>
</datamodel-type>
